lecroyscope/__init__.py
lecroyscope/version.py
lecroyscope/control/__init__.py
lecroyscope/control/scope.py
lecroyscope/reading/__init__.py
lecroyscope/reading/file.py
lecroyscope/reading/header.py
lecroyscope/reading/trace.py
lecroyscope/reading/trace_group.py
lecroyscope/writing/__init__.py
lecroyscope/writing/root/__init__.py
lecroyscope/writing/root/tree.py
lecroyscope-1.0.0.dist-info/METADATA
lecroyscope-1.0.0.dist-info/WHEEL
lecroyscope-1.0.0.dist-info/licenses/LICENSE
lecroyscope-1.0.0.dist-info/RECORD
