Metadata-Version: 2.1
Name: lecroyscope
Version: 1.0.0
Summary: An unofficial Python package 🐍📦 to interface with Teledyne LeCroy oscilloscopes and read binary trace files (.trc)
Project-URL: Download, https://github.com/lobis/lecroy-scope/releases
Project-URL: Homepage, https://github.com/lobis/lecroy-scope
Project-URL: Bug Tracker, https://github.com/lobis/lecroy-scope/issues
Author-email: Luis Antonio Obis Aparicio <luis.antonio.obis@gmail.com>
License-Expression: BSD-3-Clause
License-File: LICENSE
Keywords: binary,lecroy,oscilloscope,scope,trc,vxi11
Classifier: Operating System :: OS Independent
Classifier: Programming Language :: Python :: 3
Requires-Python: >=3.8
Requires-Dist: numpy
Requires-Dist: python-vxi11
Provides-Extra: dev
Requires-Dist: awkward; extra == 'dev'
Requires-Dist: pre-commit; extra == 'dev'
Requires-Dist: pytest; extra == 'dev'
Requires-Dist: uproot; extra == 'dev'
Provides-Extra: test
Requires-Dist: pytest; extra == 'test'
